quick_netmiko/__init__.py
quick_netmiko/quick_netmiko.py
quick_netmiko/version.py
quick_netmiko-2.0.0.dist-info/LICENSE
quick_netmiko-2.0.0.dist-info/METADATA
quick_netmiko-2.0.0.dist-info/WHEEL
quick_netmiko-2.0.0.dist-info/top_level.txt
quick_netmiko-2.0.0.dist-info/RECORD
