Metadata-Version: 2.1
Name: quick-netmiko
Version: 2.0.0
Summary: This is a way to just get commands using Netmiko
Home-page: https://quick-netmiko.readthedocs.io
Author: Benjamin P. Trachtenberg
Author-email: e_ben_75-python@yahoo.com
License: The MIT License (MIT)
Project-URL: Documentation, https://quick-netmiko.readthedocs.io/en/latest/
Project-URL: Source, https://github.com/btr1975/quick_netmiko
Project-URL: Tracker, https://github.com/btr1975/quick_netmiko/issues
Keywords: ipv4 ip multicast unicast network engineer
Classifier: Development Status :: 5 - Production/Stable
Classifier: License :: OSI Approved :: MIT License
Classifier: Intended Audience :: Developers
Classifier: Natural Language :: English
Classifier: Operating System :: MacOS :: MacOS X
Classifier: Operating System :: POSIX
Classifier: Operating System :: POSIX :: BSD
Classifier: Operating System :: POSIX :: Linux
Classifier: Operating System :: Microsoft :: Windows
Classifier: Programming Language :: Python :: 3
Classifier: Programming Language :: Python :: 3 :: Only
Classifier: Programming Language :: Python :: 3.7
Classifier: Programming Language :: Python :: 3.8
Classifier: Programming Language :: Python :: 3.9
Classifier: Programming Language :: Python :: 3.10
Requires-Python: >=3.7
License-File: LICENSE
Requires-Dist: netmiko (~=4.1.0)
